manim_svg_animations/__init__.py
manim_svg_animations/html_parsed_vmobject.py
manim_svg_animations-0.3.13.dist-info/entry_points.txt
manim_svg_animations-0.3.13.dist-info/METADATA
manim_svg_animations-0.3.13.dist-info/WHEEL
manim_svg_animations-0.3.13.dist-info/RECORD
