Metadata-Version: 2.1
Name: manim-svg-animations
Version: 0.3.13
Summary: 
Author: MathLike
Author-email: mathlikeyt@gmail.com
Requires-Python: <3.12
Classifier: Programming Language :: Python :: 2
Classifier: Programming Language :: Python :: 2.7
Classifier: Programming Language :: Python :: 3
Classifier: Programming Language :: Python :: 3.4
Classifier: Programming Language :: Python :: 3.5
Classifier: Programming Language :: Python :: 3.6
Classifier: Programming Language :: Python :: 3.7
Classifier: Programming Language :: Python :: 3.8
Classifier: Programming Language :: Python :: 3.9
Classifier: Programming Language :: Python :: 3.10
Classifier: Programming Language :: Python :: 3.11
Requires-Dist: manim (>=0.17.2,<0.18.0)
Requires-Dist: manim-mobject-svg (>=0.2.0,<0.3.0)
Requires-Dist: svgpathtools (>=1.6.0,<2.0.0)
